slack_bolt_testcase/__init__.py
slack_bolt_testcase/app_test_case.py
slack_bolt_testcase/event_test_case.py
slack_bolt_testcase/tests/__init__.py
slack_bolt_testcase/tests/test_mention_example.py
slack_bolt_testcase/tests/test_message_example.py
slack_bolt_testcase-0.0.1.dist-info/LICENSE
slack_bolt_testcase-0.0.1.dist-info/METADATA
slack_bolt_testcase-0.0.1.dist-info/WHEEL
slack_bolt_testcase-0.0.1.dist-info/top_level.txt
slack_bolt_testcase-0.0.1.dist-info/RECORD
