Metadata-Version: 2.1
Name: slack-bolt-testcase
Version: 0.0.1
Summary: Test case for your Slack bots
Home-page: https://github.com/diegojromerolopez/slack-bolt-testcase
Author: Diego J. Romero López
Author-email: diegojromerolopez@gmail.com
License: MIT
Keywords: slack unittest mock
Classifier: Programming Language :: Python :: Implementation :: CPython
Classifier: Programming Language :: Python :: Implementation :: PyPy
Classifier: Programming Language :: Python :: 3.9
Classifier: Programming Language :: Python :: 3.10
Classifier: Programming Language :: Python :: 3.11
Classifier: Programming Language :: Python :: 3.12
Classifier: Programming Language :: Python :: 3.13
Classifier: Topic :: Software Development :: Libraries
Classifier: Development Status :: 3 - Alpha
Classifier: License :: OSI Approved :: MIT License
License-File: LICENSE
Requires-Dist: slack-bolt (~=1.23.0)
Requires-Dist: slack-sdk (~=3.35.0)
